pykz/__init__.py
pykz/api.py
pykz/calc.py
pykz/command.py
pykz/constants.py
pykz/contour.py
pykz/environment.py
pykz/exceptions.py
pykz/formatting.py
pykz/io.py
pykz/label.py
pykz/options.py
pykz/plot.py
pykz/style.py
pykz/tikzcode.py
pykz/tikzgen.py
pykz/util.py
pykz/commands/__init__.py
pykz/commands/addplot.py
pykz/commands/circle.py
pykz/commands/connector.py
pykz/commands/draw.py
pykz/commands/fillbetween.py
pykz/commands/node.py
pykz/commands/tikzset.py
pykz/environments/__init__.py
pykz/environments/axis.py
pykz/environments/tikzpicture.py
pykz-0.2.3.dist-info/licenses/LICENSE
pykz-0.2.3.dist-info/WHEEL
pykz-0.2.3.dist-info/METADATA
pykz-0.2.3.dist-info/RECORD
