Metadata-Version: 2.4
Name: pykz
Version: 0.2.3
Summary: A Matplotlib-like interface for generating Tikz and Pgfplots figures
Keywords: tikz,plotting,matplotlib,pgfplots,latex
Author-email: Mathijs Schuurmans <mathijs.schuurmans@optia.be>
Requires-Python: >=3.7
Classifier: Development Status :: 5 - Production/Stable
Classifier: Intended Audience :: Science/Research
Classifier: License :: OSI Approved :: GNU General Public License v2 (GPLv2)
Classifier: Topic :: Multimedia :: Graphics
Classifier: Topic :: Scientific/Engineering
Classifier: Topic :: Scientific/Engineering :: Mathematics
Classifier: Topic :: Text Processing :: Markup :: LaTeX
Classifier: Topic :: Artistic Software
Classifier: Topic :: Software Development :: Code Generators
Classifier: Programming Language :: Python :: 3
Classifier: Programming Language :: Python :: 3.7
Classifier: Programming Language :: Python :: 3.8
Classifier: Programming Language :: Python :: 3.9
Classifier: Programming Language :: Python :: 3.10
Classifier: Programming Language :: Python :: 3.11
Classifier: Programming Language :: Python :: 3.12
Classifier: Programming Language :: Python :: 3.13
Classifier: Operating System :: POSIX :: Linux
Classifier: Operating System :: Microsoft :: Windows
Classifier: Operating System :: MacOS
License-File: LICENSE
Requires-Dist: numpy>=1.9
Requires-Dist: contourpy>=1.3
Requires-Dist: pytest ; extra == "dev"
Requires-Dist: sphinx ; extra == "dev"
Requires-Dist: pydata-sphinx-theme ; extra == "dev"
Requires-Dist: myst_parser ; extra == "dev"
Requires-Dist: sphinx-gallery ; extra == "dev"
Requires-Dist: sphinx-codeautolink ; extra == "dev"
Requires-Dist: matplotlib ; extra == "dev"
Requires-Dist: pdf2image ; extra == "dev"
Requires-Dist: pdf2image ; extra == "png"
Project-URL: Bug Tracker, https://github.com/Mathijssch/pykz/issues
Project-URL: Documentation, https://mathijssch.github.io/pykz
Project-URL: Source, https://github.com/Mathijssch/pykz
Provides-Extra: dev
Provides-Extra: png
